odoo8_addon_stock_route_sales_team-8.0.1.0.0.99.dev15-py3.8-nspkg.pth
odoo_addons/stock_route_sales_team/README.rst
odoo_addons/stock_route_sales_team/__init__.py
odoo_addons/stock_route_sales_team/__openerp__.py
odoo_addons/stock_route_sales_team/i18n/ca.po
odoo_addons/stock_route_sales_team/i18n/de.po
odoo_addons/stock_route_sales_team/i18n/es.po
odoo_addons/stock_route_sales_team/i18n/es_ES.po
odoo_addons/stock_route_sales_team/i18n/fi.po
odoo_addons/stock_route_sales_team/i18n/fr.po
odoo_addons/stock_route_sales_team/i18n/hr.po
odoo_addons/stock_route_sales_team/i18n/hu.po
odoo_addons/stock_route_sales_team/i18n/it.po
odoo_addons/stock_route_sales_team/i18n/nl.po
odoo_addons/stock_route_sales_team/i18n/nl_NL.po
odoo_addons/stock_route_sales_team/i18n/pt_BR.po
odoo_addons/stock_route_sales_team/i18n/ro.po
odoo_addons/stock_route_sales_team/i18n/sk.po
odoo_addons/stock_route_sales_team/i18n/sl.po
odoo_addons/stock_route_sales_team/i18n/stock_route_sales_team.pot
odoo_addons/stock_route_sales_team/i18n/tr.po
odoo_addons/stock_route_sales_team/i18n/tr_TR.po
odoo_addons/stock_route_sales_team/i18n/zh_CN.po
odoo_addons/stock_route_sales_team/model/__init__.py
odoo_addons/stock_route_sales_team/model/crm_case_section.py
odoo_addons/stock_route_sales_team/model/sale_order.py
odoo_addons/stock_route_sales_team/model/stock_location_route.py
odoo_addons/stock_route_sales_team/static/description/icon.png
odoo_addons/stock_route_sales_team/tests/__init__.py
odoo_addons/stock_route_sales_team/tests/test_sale_team_route.py
odoo_addons/stock_route_sales_team/view/crm_case_section_view.xml
odoo_addons/stock_route_sales_team/view/stock_location_route_view.xml
odoo8_addon_stock_route_sales_team-8.0.1.0.0.99.dev15.dist-info/METADATA
odoo8_addon_stock_route_sales_team-8.0.1.0.0.99.dev15.dist-info/WHEEL
odoo8_addon_stock_route_sales_team-8.0.1.0.0.99.dev15.dist-info/namespace_packages.txt
odoo8_addon_stock_route_sales_team-8.0.1.0.0.99.dev15.dist-info/top_level.txt
odoo8_addon_stock_route_sales_team-8.0.1.0.0.99.dev15.dist-info/RECORD
